cgnize/__init__.py
cgnize/extract_variables.py
cgnize-0.2.9.dist-info/METADATA
cgnize-0.2.9.dist-info/WHEEL
cgnize-0.2.9.dist-info/top_level.txt
cgnize-0.2.9.dist-info/RECORD
