Metadata-Version: 2.4
Name: cgnize
Version: 0.2.9
Summary: A Python toolkit for parsing, reading, and organizing cgns data files into analysis-ready format.
Author-email: Jonathan Motta <jonathan.motta@safesolutions.com.br>
Project-URL: Homepage, https://github.com/Safe-Solutions-Engenharia/cgnize
Project-URL: Bug Tracker, https://github.com/Safe-Solutions-Engenharia/cgnize/issues
Classifier: Programming Language :: Python :: 3
Classifier: Operating System :: OS Independent
Classifier: Intended Audience :: Science/Research
Classifier: Topic :: Scientific/Engineering
Requires-Python: >=3.10
Requires-Dist: numpy
Requires-Dist: pandas
Requires-Dist: numba
Requires-Dist: h5py
